arcrest/__init__.py
arcrest/ago.py
arcrest/compat.py
arcrest/geometry.py
arcrest/gptypes.py
arcrest/portal.py
arcrest/projections.py
arcrest/server.py
arcrest/utils.py
arcrest/admin/__init__.py
arcrest/admin/admin_objects.py
arcrest/admin/cmdline.py
gn_arcrest-10.5.5.data/scripts/convertcachestorageformat.py
gn_arcrest-10.5.5.data/scripts/createcacheschema.py
gn_arcrest-10.5.5.data/scripts/createservice.py
gn_arcrest-10.5.5.data/scripts/deletecache.py
gn_arcrest-10.5.5.data/scripts/managecachetiles.py
gn_arcrest-10.5.5.data/scripts/manageservice.py
gn_arcrest-10.5.5.data/scripts/managesite.py
gn_arcrest-10.5.5.data/scripts/reportcachestatus.py
gn_arcrest-10.5.5.dist-info/LICENSE
gn_arcrest-10.5.5.dist-info/METADATA
gn_arcrest-10.5.5.dist-info/WHEEL
gn_arcrest-10.5.5.dist-info/top_level.txt
gn_arcrest-10.5.5.dist-info/RECORD
